ods_types/__init__.py
ods_types/common.py
ods_types/enums.py
ods_types_py-0.1.8.dist-info/METADATA
ods_types_py-0.1.8.dist-info/WHEEL
ods_types_py-0.1.8.dist-info/top_level.txt
ods_types_py-0.1.8.dist-info/RECORD
