Metadata-Version: 2.4
Name: ods-types-py
Version: 0.1.8
Summary: Core types and enums for ODS (Optikka Design System) - Python implementation
Author-email: Optikka <dev@optikka.com>
License: PROPRIETARY
Project-URL: Homepage, https://github.com/optikka/ods
Project-URL: Repository, https://github.com/optikka/ods
Keywords: ods,types,enums,renderer,optikka
Classifier: Development Status :: 4 - Beta
Classifier: Intended Audience :: Developers
Classifier: Programming Language :: Python :: 3
Classifier: Programming Language :: Python :: 3.11
Classifier: Programming Language :: Python :: 3.12
Classifier: Programming Language :: Python :: 3.13
Requires-Python: >=3.11
Provides-Extra: dev
Requires-Dist: pytest>=7.4.0; extra == "dev"
Requires-Dist: pytest-cov>=4.1.0; extra == "dev"
Requires-Dist: black>=23.0.0; extra == "dev"
Requires-Dist: ruff>=0.1.0; extra == "dev"
Requires-Dist: mypy>=1.5.0; extra == "dev"
